fyne/__init__.py
fyne/blackscholes.py
fyne/common.py
fyne/heston.py
fyne/wishart/__init__.py
fyne/wishart/core.py
fyne/wishart/rotation_count.py
fyne/wishart/utils.py
fyne-0.6.4.dist-info/AUTHORS.rst
fyne-0.6.4.dist-info/LICENSE
fyne-0.6.4.dist-info/METADATA
fyne-0.6.4.dist-info/WHEEL
fyne-0.6.4.dist-info/top_level.txt
fyne-0.6.4.dist-info/RECORD
