Metadata-Version: 2.1
Name: fyne
Version: 0.6.4
Summary: The Python module for option pricing with affine models.
Home-page: https://github.com/dougmvieira/fyne
Author: Douglas Machado Vieira
Author-email: dougmvieira@gmail.com
License: MIT license
Project-URL: Documentation, https://fyne.readthedocs.io/
Project-URL: Changelog, https://fyne.readthedocs.io/en/latest/changelog.html
Project-URL: Issue Tracker, https://github.com/dougmvieira/fyne/issues
Platform: UNKNOWN
Classifier: Development Status :: 5 - Production/Stable
Classifier: Intended Audience :: Developers
Classifier: License :: OSI Approved :: MIT License
Classifier: Operating System :: Unix
Classifier: Operating System :: POSIX
Classifier: Operating System :: Microsoft :: Windows
Classifier: Programming Language :: Python
Classifier: Programming Language :: Python :: 3
Classifier: Programming Language :: Python :: 3.6
Classifier: Programming Language :: Python :: 3.7
Classifier: Programming Language :: Python :: 3.8
Classifier: Programming Language :: Python :: Implementation :: CPython
Classifier: Programming Language :: Python :: Implementation :: PyPy
Classifier: Topic :: Utilities
Requires-Python: >=3.6
Requires-Dist: numpy
Requires-Dist: numba
Requires-Dist: scipy
Requires-Dist: py-lets-be-rational
